{
  "auditDate": "2025-08-27",
  "auditScope": "Admin area dependencies",
  "auditType": "READ-ONLY",
  "summary": {
    "totalFilesAnalyzed": 15,
    "usedFiles": 7,
    "unusedFiles": 4,
    "duplicateFiles": 8,
    "backupFiles": 1
  },
  "htmlIncludes": {
    "admin.html": {
      "css": ["css/styles.css"],
      "js": ["js/script.js"],
      "inlineJS": true,
      "location": "root",
      "duplicate": "public/admin.html"
    },
    "admin-login.html": {
      "css": ["css/styles.css"],
      "js": ["admin/config.js", "js/script.js"],
      "inlineJS": true,
      "location": "root",
      "duplicate": "public/admin-login.html"
    },
    "admin.backup-20250827-113019.html": {
      "css": ["css/styles.css"],
      "js": ["js/script.js"],
      "inlineJS": true,
      "status": "backup-preserve"
    }
  },
  "javascriptTouchpoints": {
    "domSelectors": {
      "getElementById": 47,
      "querySelector": 25,
      "querySelectorAll": 15,
      "getElementsByTagName": 4,
      "getElementsByClassName": 2
    },
    "criticalElements": [
      "admin-login-form",
      "admin-password", 
      "client-name",
      "session-type",
      "gallery-code",
      "gallery-password",
      "expiration-date",
      "upload-zone",
      "file-input",
      "upload-status",
      "create-gallery-btn",
      "refresh-galleries-btn"
    ],
    "apiEndpoints": [
      "https://4l12h6snuh.execute-api.us-east-1.amazonaws.com/upload",
      "https://4l12h6snuh.execute-api.us-east-1.amazonaws.com/delete-gallery",
      "https://hhk9mnddq4.execute-api.us-east-1.amazonaws.com/prod/contact"
    ]
  },
  "fileUsageStatus": {
    "used": [
      {
        "file": "css/styles.css",
        "referencedBy": ["admin.html", "admin-login.html", "public copies"],
        "purpose": "Main site styling"
      },
      {
        "file": "js/script.js", 
        "referencedBy": ["admin.html", "admin-login.html", "public copies"],
        "purpose": "Site functionality, cursor, forms"
      },
      {
        "file": "admin/config.js",
        "referencedBy": ["admin-login.html", "public copy"],
        "purpose": "Admin authentication config"
      }
    ],
    "unused": [
      {
        "file": "admin/admin.js",
        "reason": "Tab management system not implemented",
        "size_estimate": "2KB",
        "safe_to_remove": true
      },
      {
        "file": "admin/admin.galleries.js",
        "reason": "Gallery functions superseded by inline code",
        "size_estimate": "2KB", 
        "safe_to_remove": true
      },
      {
        "file": "admin/admin.selections.js",
        "reason": "Selection system not implemented",
        "size_estimate": "2KB",
        "safe_to_remove": true
      },
      {
        "file": "admin/admin.css",
        "reason": "Not referenced in any HTML",
        "size_estimate": "2KB",
        "safe_to_remove": true
      }
    ]
  },
  "duplicates": {
    "root_vs_public": [
      {
        "root": "admin.html",
        "public": "public/admin.html",
        "status": "identical",
        "recommendation": "Keep root as master"
      },
      {
        "root": "admin-login.html", 
        "public": "public/admin-login.html",
        "status": "identical",
        "recommendation": "Keep root as master"
      },
      {
        "root": "admin/config.js",
        "public": "public/admin/config.js", 
        "status": "identical",
        "recommendation": "Sync from root"
      }
    ]
  },
  "backupFiles": [
    {
      "file": "admin.backup-20250827-113019.html",
      "date": "2025-08-27 11:30:19",
      "purpose": "Original admin backup before tab implementation attempt",
      "recommendation": "PRESERVE - Contains working admin interface"
    }
  ],
  "tabPagesAnalysis": {
    "currentImplementation": "Single page with 3 sections",
    "sections": [
      "Active Galleries (table)",
      "Create New Gallery (form)",
      "Quick Stats (dashboard)"
    ],
    "originalTabVision": {
      "implemented": false,
      "evidence": "Unused admin.js contains tab management code",
      "plannedTabs": 10,
      "status": "Abandoned for single-page layout"
    }
  },
  "securityFindings": [
    {
      "type": "hardcoded_credentials",
      "location": "admin/config.js",
      "details": "Admin password 'cinematics123' in plaintext",
      "severity": "medium",
      "note": "Marked as staging/dev only"
    },
    {
      "type": "keyboard_shortcut",
      "location": "js/script.js line 674",
      "details": "Secret admin access via Ctrl+Shift+\\",
      "severity": "low",
      "note": "Easter egg for admin access"
    }
  ],
  "cleanupRecommendations": {
    "immediate_safe_removal": [
      "admin/admin.js",
      "admin/admin.galleries.js", 
      "admin/admin.selections.js",
      "admin/admin.css"
    ],
    "estimated_space_saved": "8KB",
    "file_organization": {
      "keep_root_as_master": true,
      "sync_public_from_root": true,
      "preserve_backup": true
    }
  },
  "deploymentStructure": {
    "localServer": "Serves from public/ directory",
    "staging": "Uses root files",
    "fileFlow": "root -> public (deployment copies)"
  }
}